kvs.py
KVS-1.0.0.dist-info/DESCRIPTION.rst
KVS-1.0.0.dist-info/METADATA
KVS-1.0.0.dist-info/RECORD
KVS-1.0.0.dist-info/WHEEL
KVS-1.0.0.dist-info/metadata.json
KVS-1.0.0.dist-info/top_level.txt
